film/__init__.py
film/demo.py
film/film.py
film/frame/lancer_marteau
film/frame/poursuiteci
film/frame/poursuiteic
film/frame/roflcopter
film/frame/roflflyingcat
film/frame/roflflyingmoto
film/frame/roflplane
film/frames/bon00
film/frames/bon10
film/frames/bon20
film/frames/bon30
ascii_films-0.0.18.dist-info/LICENCE
ascii_films-0.0.18.dist-info/METADATA
ascii_films-0.0.18.dist-info/WHEEL
ascii_films-0.0.18.dist-info/top_level.txt
ascii_films-0.0.18.dist-info/RECORD
