Metadata-Version: 2.1
Name: ascii-films
Version: 0.0.18
Summary: Cette classe fournit des outils pour afficher des petits films à partir de frames en ascii.
Home-page: https://framagit.org/zenjo/film/wikis/home
Author: Robert Sebille
Author-email: robert@sebille.name
Maintainer: Robert Sebille
Maintainer-email: robert@sebille.name
License: GNU GPL
Download-URL: https://framagit.org/zenjo/film/tree/master
Platform: UNKNOWN
Classifier: Programming Language :: Python :: 3
Classifier: License :: OSI Approved :: GNU General Public License (GPL)
Classifier: Operating System :: OS Independent
